soco/__init__.py
soco/alarms.py
soco/cache.py
soco/config.py
soco/core.py
soco/data_structure_quirks.py
soco/data_structures.py
soco/data_structures_entry.py
soco/discovery.py
soco/events.py
soco/events_asyncio.py
soco/events_base.py
soco/events_twisted.py
soco/exceptions.py
soco/groups.py
soco/ms_data_structures.py
soco/music_library.py
soco/services.py
soco/snapshot.py
soco/soap.py
soco/utils.py
soco/xml.py
soco/zonegroupstate.py
soco/music_services/__init__.py
soco/music_services/accounts.py
soco/music_services/data_structures.py
soco/music_services/music_service.py
soco/music_services/token_store.py
soco/plugins/__init__.py
soco/plugins/example.py
soco/plugins/plex.py
soco/plugins/sharelink.py
soco/plugins/spotify.py
soco/plugins/wimp.py
soco-0.30.13.dist-info/licenses/AUTHORS.rst
soco-0.30.13.dist-info/licenses/LICENSE.rst
soco-0.30.13.dist-info/METADATA
soco-0.30.13.dist-info/WHEEL
soco-0.30.13.dist-info/top_level.txt
soco-0.30.13.dist-info/RECORD
