Metadata-Version: 2.4
Name: soco
Version: 0.30.13
Summary: SoCo (Sonos Controller) is a simple library to control Sonos speakers.
Author-email: The SoCo-Team <python-soco@googlegroups.com>
License: MIT License
Project-URL: Homepage, https://github.com/SoCo/SoCo
Classifier: Development Status :: 4 - Beta
Classifier: Intended Audience :: Developers
Classifier: License :: OSI Approved :: MIT License
Classifier: Operating System :: OS Independent
Classifier: Programming Language :: Python :: 3.6
Classifier: Programming Language :: Python :: 3.7
Classifier: Programming Language :: Python :: 3.8
Classifier: Programming Language :: Python :: 3.9
Classifier: Programming Language :: Python :: 3 :: Only
Classifier: Programming Language :: Python :: Implementation :: CPython
Classifier: Programming Language :: Python :: Implementation :: PyPy
Classifier: Topic :: Home Automation
Classifier: Topic :: Multimedia :: Sound/Audio
Classifier: Topic :: Multimedia :: Sound/Audio :: Players
Classifier: Topic :: Software Development :: Libraries :: Python Modules
Requires-Python: >=3.6
License-File: LICENSE.rst
License-File: AUTHORS.rst
Requires-Dist: requests
Requires-Dist: xmltodict
Requires-Dist: ifaddr
Requires-Dist: appdirs
Requires-Dist: lxml
Provides-Extra: events-asyncio
Requires-Dist: aiohttp; extra == "events-asyncio"
Provides-Extra: testing
Requires-Dist: sphinx==4.5.0; extra == "testing"
Requires-Dist: sphinx_rtd_theme; extra == "testing"
Requires-Dist: pytest>=2.5; extra == "testing"
Requires-Dist: graphviz; extra == "testing"
Requires-Dist: flake8; extra == "testing"
Requires-Dist: pylint; extra == "testing"
Requires-Dist: coveralls; extra == "testing"
Requires-Dist: pytest-cov<2.6.0; extra == "testing"
Requires-Dist: wheel; extra == "testing"
Requires-Dist: black>=22.12.0; python_version >= "3.7" and extra == "testing"
Requires-Dist: requests-mock; extra == "testing"
Requires-Dist: twine; extra == "testing"
Requires-Dist: importlib-metadata<5; python_version == "3.7" and extra == "testing"
Dynamic: license-file
